Metadata-Version: 1.1
Name: shttpd
Version: 0.0.5
Summary: Simple HTTP downloader written in Python
Home-page: https://github.com/RDCH106/pySimpleHTTPDownloader
Author: Rubén de Celis Hernández
Author-email: contact@rdch106.hol.es
License: LGPL v3
Download-URL: https://github.com/RDCH106/pySimpleHTTPDownloader/archive/v0.0.5.tar.gz
Keywords: http downloader
Platform: UNKNOWN
Classifier: Programming Language :: Python
Classifier: Programming Language :: Python :: 3.2
Classifier: Programming Language :: Python :: 3.3
Classifier: Programming Language :: Python :: 3.4
Classifier: Programming Language :: Python :: 3.5
Classifier: Programming Language :: Python :: 3.6
